<?xml version="1.0" encoding="utf-8"?>
<script xmlns:xsd="http://www.w3.org/2001/XMLSchema" xmlns:xsi="http://www.w3.org/2001/XMLSchema-instance">
    <dialogueEmeline id="1">
      <time>
        <hour>17</hour>
        <minutes>07</minutes>
      </time>
      <date>
        <year>2019</year>
        <month>11</month>
        <day>22</day>
      </date>
      <message>
        Lol viens te battre !
      </message>
      <next>002</next>
    </dialogueEmeline>
    <dialogueJoueur id="002">
      <reponse>
        <valueChange>15</valueChange>
        <txtReponse>Oui!</txtReponse>
        <next>003</next>
      </reponse>
      <reponse>
        <valueChange>3</valueChange>
        <txtReponse>Non!</txtReponse>
        <next>004</next>
      </reponse>
      <reponse>
        <valueChange>-66</valueChange>
        <txtReponse>Pourquoi?</txtReponse>
        <next>005</next>
      </reponse>
    </dialogueJoueur>
</script>